{
  "db_name": "SQLite",
  "query": "SELECT id, name, variables, created_at, updated_at, archived_at FROM environments WHERE id = ?",
  "describe": {
    "columns": [
      {
        "name": "id",
        "ordinal": 0,
        "type_info": "Integer"
      },
      {
        "name": "name",
        "ordinal": 1,
        "type_info": "Text"
      },
      {
        "name": "variables",
        "ordinal": 2,
        "type_info": "Text"
      },
      {
        "name": "created_at",
        "ordinal": 3,
        "type_info": "Datetime"
      },
      {
        "name": "updated_at",
        "ordinal": 4,
        "type_info": "Datetime"
      },
      {
        "name": "archived_at",
        "ordinal": 5,
        "type_info": "Datetime"
      }
    ],
    "parameters": {
      "Right": 1
    },
    "nullable": [
      false,
      false,
      false,
      false,
      false,
      true
    ]
  },
  "hash": "0721ce7856fbec584d451756a3ae9446856a8ac8df75f06bf320b74bcfc805ce"
}
